fastfilter/_about.cpython-311-i386-linux-musl.so
fastfilter/__init__.py
fastfilter/filter.cpython-311-i386-linux-musl.so
fastfilter-0.0.4.dist-info/RECORD
fastfilter-0.0.4.dist-info/WHEEL
fastfilter-0.0.4.dist-info/METADATA
fastfilter-0.0.4.dist-info/licenses/LICENSE
