Metadata-Version: 2.1
Name: fastfilter
Version: 0.0.4
Summary: High-Performance Linear/Non-Linear Filters and Window Functions Library in C++ with Python Bindings
Author-Email: Mohammad Raziei <mohammadraziei1375@gmail.com>
Classifier: Development Status :: 4 - Beta
Classifier: License :: OSI Approved :: MIT License
Classifier: Operating System :: OS Independent
Classifier: Programming Language :: C++
Classifier: Programming Language :: Python :: Implementation :: CPython
Classifier: Programming Language :: Python :: 3 :: Only
Classifier: Programming Language :: Python :: 3.8
Classifier: Programming Language :: Python :: 3.9
Classifier: Programming Language :: Python :: 3.10
Classifier: Programming Language :: Python :: 3.11
Project-URL: Homepage, https://github.com/mohammadraziei/fastfilter
Project-URL: Bug tracker, https://github.com/mohammadraziei/fastfilter/issues
Project-URL: Document, https://mohammadraziei.github.io/fastfilter/latest
Requires-Python: >=3.8
Provides-Extra: test
Requires-Dist: pytest; extra == "test"
Requires-Dist: numpy; extra == "test"
Requires-Dist: scipy; extra == "test"
